deluge_client/__init__.py
deluge_client/client.py
deluge_client/rencode.py
deluge_client/tests.py
deluge_client-1.10.0.dist-info/LICENSE
deluge_client-1.10.0.dist-info/METADATA
deluge_client-1.10.0.dist-info/WHEEL
deluge_client-1.10.0.dist-info/top_level.txt
deluge_client-1.10.0.dist-info/RECORD
