Metadata-Version: 2.1
Name: deluge-client
Version: 1.10.0
Summary: Simple Deluge Client
Home-page: https://github.com/JohnDoee/deluge-client
Author: Anders Jensen
Author-email: andersandjensen@gmail.com
Maintainer: John Doee
License: MIT
Classifier: Development Status :: 4 - Beta
Classifier: License :: OSI Approved :: MIT License
Classifier: Programming Language :: Python :: 3.8
Classifier: Programming Language :: Python :: 3.9
Classifier: Programming Language :: Python :: 3.10
Classifier: Programming Language :: Python :: 3.11
Classifier: Programming Language :: Python :: 3.12
Classifier: Topic :: Software Development :: Libraries :: Python Modules
License-File: LICENSE
